zipslicer/__init__.py
zipslicer/custom_load.py
zipslicer/weights_only_unpickler.py
zipslicer-0.8.1.dist-info/LICENSE
zipslicer-0.8.1.dist-info/METADATA
zipslicer-0.8.1.dist-info/WHEEL
zipslicer-0.8.1.dist-info/top_level.txt
zipslicer-0.8.1.dist-info/RECORD
