Metadata-Version: 2.1
Name: zipslicer
Version: 0.8.1
Summary: A library for efficient incremental access to tensors stored in PyTorch checkpoints
Home-page: https://github.com/kir-gadjello/zipslicer
Author: Kirill Gadjello
Author-email: kirill.gadjello@protonmail.com
License: BSD-3
Keywords: pytorch,machine learning
Classifier: Development Status :: 5 - Production/Stable
Classifier: Intended Audience :: Developers
Classifier: Intended Audience :: Education
Classifier: Intended Audience :: Science/Research
Classifier: License :: OSI Approved :: BSD License
Classifier: Topic :: Scientific/Engineering
Classifier: Topic :: Scientific/Engineering :: Mathematics
Classifier: Topic :: Scientific/Engineering :: Artificial Intelligence
Classifier: Topic :: Software Development
Classifier: Topic :: Software Development :: Libraries
Classifier: Topic :: Software Development :: Libraries :: Python Modules
Classifier: Programming Language :: Python :: 3
Classifier: Programming Language :: Python :: 3.8
Classifier: Programming Language :: Python :: 3.9
Classifier: Programming Language :: Python :: 3.10
Classifier: Programming Language :: Python :: 3.11
Requires-Python: >=3
License-File: LICENSE
Requires-Dist: torch (>=1.10.0)
Provides-Extra: dev
Requires-Dist: pytest (>=3.10) ; extra == 'dev'
